{
  "case_001": [
    {
      "documentId": "rad_001",
      "sourceType": "radiology_report",
      "date": "2026-04-10",
      "modality": "abdomen_ultrasound",
      "radiologist": "Dr. Selin Doğan",
      "finding": "Karaciğer boyut ve ekojenite açısından normal görünümde. Safra kesesi duvar kalınlığı normal, taş izlenmedi. Pankreas gövde ve kuyruğu yeterince değerlendirilemedi (bağırsak gazı nedeniyle). Belirgin akut patoloji izlenmedi.",
      "impression": "Belirgin akut patoloji izlenmedi. Pankreas yeterince değerlendirilemedi; klinik şüphe devam ediyorsa BT önerilir.",
      "followupRecommendation": "Klinik şüphe devam ediyorsa abdomen BT önerilir."
    }
  ],
  "case_002": [
    {
      "documentId": "rad_cardio_1",
      "sourceType": "radiology_report",
      "date": "2026-06-15",
      "modality": "echocardiogram",
      "radiologist": "Dr. Veli Taş",
      "finding": "Sol ventrikül ejeksiyon fraksiyonu %45. Segmenter duvar hareket bozukluğu mevcut.",
      "impression": "Hafif azalmış sol ventrikül fonksiyonu.",
      "followupRecommendation": "Kardiyoloji poliklinik kontrolü önerilir."
    }
  ],
  "case_003": [
    {
      "documentId": "rad_pulm_1",
      "sourceType": "radiology_report",
      "date": "2026-06-20",
      "modality": "chest_xray",
      "radiologist": "Dr. Zeynep Can",
      "finding": "Bilateral akciğer alanları havalanması normaldir. Pnömokonyoz bulgusu saptanmadı. Kalp gölgesi normal.",
      "impression": "Normal sınırda PA akciğer grafisi.",
      "followupRecommendation": ""
    }
  ]
}
